hw1/hw1_2/nand2.v
module nand2 (in1,in2,out);
input in1,in2;
output out;
assign out = ~(in1 & in2);
endmodule

hw1/hw1_3/xor2.v
module xor2 (in1,in2,out);
input in1,in2;
output out;
assign out = in1 ^ in2;
endmodule

hw1/hw1_2/fulladder.v
module fulladder(A, B, Cin, S, Cout);

  input A, B, Cin;
  output S, Cout;

  //needed wires to connect gate outputs together
  wire w1, w2, w3;

  //summation part of adder
  xor2 x1(.in1(A), .in2(B), .out(w1));
  xor2 x2(.in1(w1), .in2(Cin), .out(S));

  //Cout gates
  nand2 na1(.in1(A), .in2(B), .out(w2));
  nand2 na2(.in1(Cin), .in2(w1), .out(w3));
  nand2 na3(.in1(w3), .in2(w2), .out(Cout));

endmodule

hw1/hw1_2/fulladder4.v
module fulladder4(A, B, CI, SUM, CO);
  
  input [3:0] A, B;
  input CI;
  output [3:0] SUM;
  output CO;

  wire c1, c2, c3;

  fulladder fa3(.A(A[3]), .B(B[3]), .Cin(c3), .S(SUM[3]), .Cout(CO));
  fulladder fa2(.A(A[2]), .B(B[2]), .Cin(c2), .S(SUM[2]), .Cout(c3));
  fulladder fa1(.A(A[1]), .B(B[1]), .Cin(c1), .S(SUM[1]), .Cout(c2));
  fulladder fa0(.A(A[0]), .B(B[0]), .Cin(CI), .S(SUM[0]), .Cout(c1));

endmodule

hw1/hw1_2/fulladder16.v
module fulladder16(A, B, SUM, CO);

  input [15:0] A, B;
  output [15:0] SUM;
  output CO;

  wire co1, co2, co3;

  fulladder4 fa3(.A(A[15:12]), .B(B[15:12]), .CI(co3), .SUM(SUM[15:12]), .CO(CO));
  fulladder4 fa2(.A(A[11:8]), .B(B[11:8]), .CI(co2), .SUM(SUM[11:8]), .CO(co3));
  fulladder4 fa1(.A(A[7:4]), .B(B[7:4]), .CI(co1), .SUM(SUM[7:4]), .CO(co2));
  fulladder4 fa0(.A(A[3:0]), .B(B[3:0]), .CI(1'b0), .SUM(SUM[3:0]), .CO(co1));

endmodule

hw2/hw2_1/clkrst.v
/* $Author: karu $ */
/* $LastChangedDate: 2009-03-04 23:09:45 -0600 (Wed, 04 Mar 2009) $ */
/* $Rev: 45 $ */
// clock and reset generator
// CS/ECE 552
// Andy Phelps (TA)
// 3/22/06

// Clock period is 100 time units, and reset length
// to 201 time units (two rising edges of clock).

module clkrst (clk, rst, err);

    output clk;
    output rst;
    input  err;

    reg clk;
    reg rst;
    integer cycle_count;

    initial begin
      $dumpvars;
      cycle_count = 0;
      rst = 1;
      clk = 1;
      #201 rst = 0; // delay until slightly after two clock periods
    end

    always #50 begin   // delay 1/2 clock period each time thru loop
      clk = ~clk;
      if (clk & err) begin
        $display("Error signal asserted");
        $stop;
      end
    end

    always @(posedge clk) begin
    	cycle_count = cycle_count + 1;
	if (cycle_count > 100000) begin
		$display("hmm....more than 100000 cycles of simulation...error?\n");
		$finish;
	end
    end


endmodule
// DUMMY LINE FOR REV CONTROL :0:

hw1/hw1_2/fulladder_bench.v
module fulladder_bench;

   reg [16:0] A;
   reg [16:0] B;
   reg [16:0] Sumcalc;
   
   wire [15:0] SUM;
   wire        CO;
   wire	       Clk;
   //2 dummy wires
   wire rst;
   wire err;
   clkrst my_clkrst( .clk(Clk), .rst(rst), .err(err));
   fulladder16 DUT (.A(A[15:0]), .B(B[15:0]), .SUM(SUM), .CO(CO));
   
  
   initial
     begin
	A = 17'b0_0000_0000_0000_0000;
	B = 17'b0_0000_0000_0000_0000;
	#3200 $finish;
     end
   
   always@(posedge Clk) 
     begin
	A[15:0] = $random;
	B[15:0] = $random;
     end
   
   always@(negedge Clk)
     begin
	Sumcalc = A+B;
	$display("A : %x, B%x, Sum %x", A, B, SUM);
	
	if (Sumcalc[15:0] !== SUM) $display ("ERRORCHECK Sum error");
	if (Sumcalc[16] !== CO) $display ("ERRORCHECK CO error");
     end
   
endmodule // tb_fulladder

hw1/hw1_2/dump.vcd
$date
	Mon Sep 21 13:09:26 2020
$end
$version
	ModelSim Version 10.7c
$end
$timescale
	1ns
$end

$scope module fulladder_bench $end
$var reg 17 ! A [16:0] $end
$var reg 17 " B [16:0] $end
$var reg 17 # Sumcalc [16:0] $end
$var wire 1 $ SUM [15] $end
$var wire 1 % SUM [14] $end
$var wire 1 & SUM [13] $end
$var wire 1 ' SUM [12] $end
$var wire 1 ( SUM [11] $end
$var wire 1 ) SUM [10] $end
$var wire 1 * SUM [9] $end
$var wire 1 + SUM [8] $end
$var wire 1 , SUM [7] $end
$var wire 1 - SUM [6] $end
$var wire 1 . SUM [5] $end
$var wire 1 / SUM [4] $end
$var wire 1 0 SUM [3] $end
$var wire 1 1 SUM [2] $end
$var wire 1 2 SUM [1] $end
$var wire 1 3 SUM [0] $end
$var wire 1 4 CO $end
$var wire 1 5 Clk $end
$var wire 1 6 rst $end
$var wire 1 7 err $end

$scope module my_clkrst $end
$var reg 1 8 clk $end
$var reg 1 9 rst $end
$var wire 1 7 err $end
$var integer 32 : cycle_count $end
$upscope $end

$scope module DUT $end
$var wire 1 ; A [15] $end
$var wire 1 < A [14] $end
$var wire 1 = A [13] $end
$var wire 1 > A [12] $end
$var wire 1 ? A [11] $end
$var wire 1 @ A [10] $end
$var wire 1 A A [9] $end
$var wire 1 B A [8] $end
$var wire 1 C A [7] $end
$var wire 1 D A [6] $end
$var wire 1 E A [5] $end
$var wire 1 F A [4] $end
$var wire 1 G A [3] $end
$var wire 1 H A [2] $end
$var wire 1 I A [1] $end
$var wire 1 J A [0] $end
$var wire 1 K B [15] $end
$var wire 1 L B [14] $end
$var wire 1 M B [13] $end
$var wire 1 N B [12] $end
$var wire 1 O B [11] $end
$var wire 1 P B [10] $end
$var wire 1 Q B [9] $end
$var wire 1 R B [8] $end
$var wire 1 S B [7] $end
$var wire 1 T B [6] $end
$var wire 1 U B [5] $end
$var wire 1 V B [4] $end
$var wire 1 W B [3] $end
$var wire 1 X B [2] $end
$var wire 1 Y B [1] $end
$var wire 1 Z B [0] $end
$var wire 1 $ SUM [15] $end
$var wire 1 % SUM [14] $end
$var wire 1 & SUM [13] $end
$var wire 1 ' SUM [12] $end
$var wire 1 ( SUM [11] $end
$var wire 1 ) SUM [10] $end
$var wire 1 * SUM [9] $end
$var wire 1 + SUM [8] $end
$var wire 1 , SUM [7] $end
$var wire 1 - SUM [6] $end
$var wire 1 . SUM [5] $end
$var wire 1 / SUM [4] $end
$var wire 1 0 SUM [3] $end
$var wire 1 1 SUM [2] $end
$var wire 1 2 SUM [1] $end
$var wire 1 3 SUM [0] $end
$var wire 1 4 CO $end
$var wire 1 [ co1 $end
$var wire 1 \ co2 $end
$var wire 1 ] co3 $end

$scope module fa3 $end
$var wire 1 ; A [3] $end
$var wire 1 < A [2] $end
$var wire 1 = A [1] $end
$var wire 1 > A [0] $end
$var wire 1 K B [3] $end
$var wire 1 L B [2] $end
$var wire 1 M B [1] $end
$var wire 1 N B [0] $end
$var wire 1 ] CI $end
$var wire 1 $ SUM [3] $end
$var wire 1 % SUM [2] $end
$var wire 1 & SUM [1] $end
$var wire 1 ' SUM [0] $end
$var wire 1 4 CO $end
$var wire 1 ^ c1 $end
$var wire 1 _ c2 $end
$var wire 1 ` c3 $end

$scope module fa3 $end
$var wire 1 ; A $end
$var wire 1 K B $end
$var wire 1 ` Cin $end
$var wire 1 $ S $end
$var wire 1 4 Cout $end
$var wire 1 a w1 $end
$var wire 1 b w2 $end
$var wire 1 c w3 $end

$scope module x1 $end
$var wire 1 ; in1 $end
$var wire 1 K in2 $end
$var wire 1 a out $end
$upscope $end

$scope module x2 $end
$var wire 1 a in1 $end
$var wire 1 ` in2 $end
$var wire 1 $ out $end
$upscope $end

$scope module na1 $end
$var wire 1 ; in1 $end
$var wire 1 K in2 $end
$var wire 1 b out $end
$upscope $end

$scope module na2 $end
$var wire 1 ` in1 $end
$var wire 1 a in2 $end
$var wire 1 c out $end
$upscope $end

$scope module na3 $end
$var wire 1 c in1 $end
$var wire 1 b in2 $end
$var wire 1 4 out $end
$upscope $end
$upscope $end

$scope module fa2 $end
$var wire 1 < A $end
$var wire 1 L B $end
$var wire 1 _ Cin $end
$var wire 1 % S $end
$var wire 1 ` Cout $end
$var wire 1 d w1 $end
$var wire 1 e w2 $end
$var wire 1 f w3 $end

$scope module x1 $end
$var wire 1 < in1 $end
$var wire 1 L in2 $end
$var wire 1 d out $end
$upscope $end

$scope module x2 $end
$var wire 1 d in1 $end
$var wire 1 _ in2 $end
$var wire 1 % out $end
$upscope $end

$scope module na1 $end
$var wire 1 < in1 $end
$var wire 1 L in2 $end
$var wire 1 e out $end
$upscope $end

$scope module na2 $end
$var wire 1 _ in1 $end
$var wire 1 d in2 $end
$var wire 1 f out $end
$upscope $end

$scope module na3 $end
$var wire 1 f in1 $end
$var wire 1 e in2 $end
$var wire 1 ` out $end
$upscope $end
$upscope $end

$scope module fa1 $end
$var wire 1 = A $end
$var wire 1 M B $end
$var wire 1 ^ Cin $end
$var wire 1 & S $end
$var wire 1 _ Cout $end
$var wire 1 g w1 $end
$var wire 1 h w2 $end
$var wire 1 i w3 $end

$scope module x1 $end
$var wire 1 = in1 $end
$var wire 1 M in2 $end
$var wire 1 g out $end
$upscope $end

$scope module x2 $end
$var wire 1 g in1 $end
$var wire 1 ^ in2 $end
$var wire 1 & out $end
$upscope $end

$scope module na1 $end
$var wire 1 = in1 $end
$var wire 1 M in2 $end
$var wire 1 h out $end
$upscope $end

$scope module na2 $end
$var wire 1 ^ in1 $end
$var wire 1 g in2 $end
$var wire 1 i out $end
$upscope $end

$scope module na3 $end
$var wire 1 i in1 $end
$var wire 1 h in2 $end
$var wire 1 _ out $end
$upscope $end
$upscope $end

$scope module fa0 $end
$var wire 1 > A $end
$var wire 1 N B $end
$var wire 1 ] Cin $end
$var wire 1 ' S $end
$var wire 1 ^ Cout $end
$var wire 1 j w1 $end
$var wire 1 k w2 $end
$var wire 1 l w3 $end

$scope module x1 $end
$var wire 1 > in1 $end
$var wire 1 N in2 $end
$var wire 1 j out $end
$upscope $end

$scope module x2 $end
$var wire 1 j in1 $end
$var wire 1 ] in2 $end
$var wire 1 ' out $end
$upscope $end

$scope module na1 $end
$var wire 1 > in1 $end
$var wire 1 N in2 $end
$var wire 1 k out $end
$upscope $end

$scope module na2 $end
$var wire 1 ] in1 $end
$var wire 1 j in2 $end
$var wire 1 l out $end
$upscope $end

$scope module na3 $end
$var wire 1 l in1 $end
$var wire 1 k in2 $end
$var wire 1 ^ out $end
$upscope $end
$upscope $end
$upscope $end

$scope module fa2 $end
$var wire 1 ? A [3] $end
$var wire 1 @ A [2] $end
$var wire 1 A A [1] $end
$var wire 1 B A [0] $end
$var wire 1 O B [3] $end
$var wire 1 P B [2] $end
$var wire 1 Q B [1] $end
$var wire 1 R B [0] $end
$var wire 1 \ CI $end
$var wire 1 ( SUM [3] $end
$var wire 1 ) SUM [2] $end
$var wire 1 * SUM [1] $end
$var wire 1 + SUM [0] $end
$var wire 1 ] CO $end
$var wire 1 m c1 $end
$var wire 1 n c2 $end
$var wire 1 o c3 $end

$scope module fa3 $end
$var wire 1 ? A $end
$var wire 1 O B $end
$var wire 1 o Cin $end
$var wire 1 ( S $end
$var wire 1 ] Cout $end
$var wire 1 p w1 $end
$var wire 1 q w2 $end
$var wire 1 r w3 $end

$scope module x1 $end
$var wire 1 ? in1 $end
$var wire 1 O in2 $end
$var wire 1 p out $end
$upscope $end

$scope module x2 $end
$var wire 1 p in1 $end
$var wire 1 o in2 $end
$var wire 1 ( out $end
$upscope $end

$scope module na1 $end
$var wire 1 ? in1 $end
$var wire 1 O in2 $end
$var wire 1 q out $end
$upscope $end

$scope module na2 $end
$var wire 1 o in1 $end
$var wire 1 p in2 $end
$var wire 1 r out $end
$upscope $end

$scope module na3 $end
$var wire 1 r in1 $end
$var wire 1 q in2 $end
$var wire 1 ] out $end
$upscope $end
$upscope $end

$scope module fa2 $end
$var wire 1 @ A $end
$var wire 1 P B $end
$var wire 1 n Cin $end
$var wire 1 ) S $end
$var wire 1 o Cout $end
$var wire 1 s w1 $end
$var wire 1 t w2 $end
$var wire 1 u w3 $end

$scope module x1 $end
$var wire 1 @ in1 $end
$var wire 1 P in2 $end
$var wire 1 s out $end
$upscope $end

$scope module x2 $end
$var wire 1 s in1 $end
$var wire 1 n in2 $end
$var wire 1 ) out $end
$upscope $end

$scope module na1 $end
$var wire 1 @ in1 $end
$var wire 1 P in2 $end
$var wire 1 t out $end
$upscope $end

$scope module na2 $end
$var wire 1 n in1 $end
$var wire 1 s in2 $end
$var wire 1 u out $end
$upscope $end

$scope module na3 $end
$var wire 1 u in1 $end
$var wire 1 t in2 $end
$var wire 1 o out $end
$upscope $end
$upscope $end

$scope module fa1 $end
$var wire 1 A A $end
$var wire 1 Q B $end
$var wire 1 m Cin $end
$var wire 1 * S $end
$var wire 1 n Cout $end
$var wire 1 v w1 $end
$var wire 1 w w2 $end
$var wire 1 x w3 $end

$scope module x1 $end
$var wire 1 A in1 $end
$var wire 1 Q in2 $end
$var wire 1 v out $end
$upscope $end

$scope module x2 $end
$var wire 1 v in1 $end
$var wire 1 m in2 $end
$var wire 1 * out $end
$upscope $end

$scope module na1 $end
$var wire 1 A in1 $end
$var wire 1 Q in2 $end
$var wire 1 w out $end
$upscope $end

$scope module na2 $end
$var wire 1 m in1 $end
$var wire 1 v in2 $end
$var wire 1 x out $end
$upscope $end

$scope module na3 $end
$var wire 1 x in1 $end
$var wire 1 w in2 $end
$var wire 1 n out $end
$upscope $end
$upscope $end

$scope module fa0 $end
$var wire 1 B A $end
$var wire 1 R B $end
$var wire 1 \ Cin $end
$var wire 1 + S $end
$var wire 1 m Cout $end
$var wire 1 y w1 $end
$var wire 1 z w2 $end
$var wire 1 { w3 $end

$scope module x1 $end
$var wire 1 B in1 $end
$var wire 1 R in2 $end
$var wire 1 y out $end
$upscope $end

$scope module x2 $end
$var wire 1 y in1 $end
$var wire 1 \ in2 $end
$var wire 1 + out $end
$upscope $end

$scope module na1 $end
$var wire 1 B in1 $end
$var wire 1 R in2 $end
$var wire 1 z out $end
$upscope $end

$scope module na2 $end
$var wire 1 \ in1 $end
$var wire 1 y in2 $end
$var wire 1 { out $end
$upscope $end

$scope module na3 $end
$var wire 1 { in1 $end
$var wire 1 z in2 $end
$var wire 1 m out $end
$upscope $end
$upscope $end
$upscope $end

$scope module fa1 $end
$var wire 1 C A [3] $end
$var wire 1 D A [2] $end
$var wire 1 E A [1] $end
$var wire 1 F A [0] $end
$var wire 1 S B [3] $end
$var wire 1 T B [2] $end
$var wire 1 U B [1] $end
$var wire 1 V B [0] $end
$var wire 1 [ CI $end
$var wire 1 , SUM [3] $end
$var wire 1 - SUM [2] $end
$var wire 1 . SUM [1] $end
$var wire 1 / SUM [0] $end
$var wire 1 \ CO $end
$var wire 1 | c1 $end
$var wire 1 } c2 $end
$var wire 1 ~ c3 $end

$scope module fa3 $end
$var wire 1 C A $end
$var wire 1 S B $end
$var wire 1 ~ Cin $end
$var wire 1 , S $end
$var wire 1 \ Cout $end
$var wire 1 !! w1 $end
$var wire 1 "! w2 $end
$var wire 1 #! w3 $end

$scope module x1 $end
$var wire 1 C in1 $end
$var wire 1 S in2 $end
$var wire 1 !! out $end
$upscope $end

$scope module x2 $end
$var wire 1 !! in1 $end
$var wire 1 ~ in2 $end
$var wire 1 , out $end
$upscope $end

$scope module na1 $end
$var wire 1 C in1 $end
$var wire 1 S in2 $end
$var wire 1 "! out $end
$upscope $end

$scope module na2 $end
$var wire 1 ~ in1 $end
$var wire 1 !! in2 $end
$var wire 1 #! out $end
$upscope $end

$scope module na3 $end
$var wire 1 #! in1 $end
$var wire 1 "! in2 $end
$var wire 1 \ out $end
$upscope $end
$upscope $end

$scope module fa2 $end
$var wire 1 D A $end
$var wire 1 T B $end
$var wire 1 } Cin $end
$var wire 1 - S $end
$var wire 1 ~ Cout $end
$var wire 1 $! w1 $end
$var wire 1 %! w2 $end
$var wire 1 &! w3 $end

$scope module x1 $end
$var wire 1 D in1 $end
$var wire 1 T in2 $end
$var wire 1 $! out $end
$upscope $end

$scope module x2 $end
$var wire 1 $! in1 $end
$var wire 1 } in2 $end
$var wire 1 - out $end
$upscope $end

$scope module na1 $end
$var wire 1 D in1 $end
$var wire 1 T in2 $end
$var wire 1 %! out $end
$upscope $end

$scope module na2 $end
$var wire 1 } in1 $end
$var wire 1 $! in2 $end
$var wire 1 &! out $end
$upscope $end

$scope module na3 $end
$var wire 1 &! in1 $end
$var wire 1 %! in2 $end
$var wire 1 ~ out $end
$upscope $end
$upscope $end

$scope module fa1 $end
$var wire 1 E A $end
$var wire 1 U B $end
$var wire 1 | Cin $end
$var wire 1 . S $end
$var wire 1 } Cout $end
$var wire 1 '! w1 $end
$var wire 1 (! w2 $end
$var wire 1 )! w3 $end

$scope module x1 $end
$var wire 1 E in1 $end
$var wire 1 U in2 $end
$var wire 1 '! out $end
$upscope $end

$scope module x2 $end
$var wire 1 '! in1 $end
$var wire 1 | in2 $end
$var wire 1 . out $end
$upscope $end

$scope module na1 $end
$var wire 1 E in1 $end
$var wire 1 U in2 $end
$var wire 1 (! out $end
$upscope $end

$scope module na2 $end
$var wire 1 | in1 $end
$var wire 1 '! in2 $end
$var wire 1 )! out $end
$upscope $end

$scope module na3 $end
$var wire 1 )! in1 $end
$var wire 1 (! in2 $end
$var wire 1 } out $end
$upscope $end
$upscope $end

$scope module fa0 $end
$var wire 1 F A $end
$var wire 1 V B $end
$var wire 1 [ Cin $end
$var wire 1 / S $end
$var wire 1 | Cout $end
$var wire 1 *! w1 $end
$var wire 1 +! w2 $end
$var wire 1 ,! w3 $end

$scope module x1 $end
$var wire 1 F in1 $end
$var wire 1 V in2 $end
$var wire 1 *! out $end
$upscope $end

$scope module x2 $end
$var wire 1 *! in1 $end
$var wire 1 [ in2 $end
$var wire 1 / out $end
$upscope $end

$scope module na1 $end
$var wire 1 F in1 $end
$var wire 1 V in2 $end
$var wire 1 +! out $end
$upscope $end

$scope module na2 $end
$var wire 1 [ in1 $end
$var wire 1 *! in2 $end
$var wire 1 ,! out $end
$upscope $end

$scope module na3 $end
$var wire 1 ,! in1 $end
$var wire 1 +! in2 $end
$var wire 1 | out $end
$upscope $end
$upscope $end
$upscope $end

$scope module fa0 $end
$var wire 1 G A [3] $end
$var wire 1 H A [2] $end
$var wire 1 I A [1] $end
$var wire 1 J A [0] $end
$var wire 1 W B [3] $end
$var wire 1 X B [2] $end
$var wire 1 Y B [1] $end
$var wire 1 Z B [0] $end
$var wire 1 -! CI $end
$var wire 1 0 SUM [3] $end
$var wire 1 1 SUM [2] $end
$var wire 1 2 SUM [1] $end
$var wire 1 3 SUM [0] $end
$var wire 1 [ CO $end
$var wire 1 .! c1 $end
$var wire 1 /! c2 $end
$var wire 1 0! c3 $end

$scope module fa3 $end
$var wire 1 G A $end
$var wire 1 W B $end
$var wire 1 0! Cin $end
$var wire 1 0 S $end
$var wire 1 [ Cout $end
$var wire 1 1! w1 $end
$var wire 1 2! w2 $end
$var wire 1 3! w3 $end

$scope module x1 $end
$var wire 1 G in1 $end
$var wire 1 W in2 $end
$var wire 1 1! out $end
$upscope $end

$scope module x2 $end
$var wire 1 1! in1 $end
$var wire 1 0! in2 $end
$var wire 1 0 out $end
$upscope $end

$scope module na1 $end
$var wire 1 G in1 $end
$var wire 1 W in2 $end
$var wire 1 2! out $end
$upscope $end

$scope module na2 $end
$var wire 1 0! in1 $end
$var wire 1 1! in2 $end
$var wire 1 3! out $end
$upscope $end

$scope module na3 $end
$var wire 1 3! in1 $end
$var wire 1 2! in2 $end
$var wire 1 [ out $end
$upscope $end
$upscope $end

$scope module fa2 $end
$var wire 1 H A $end
$var wire 1 X B $end
$var wire 1 /! Cin $end
$var wire 1 1 S $end
$var wire 1 0! Cout $end
$var wire 1 4! w1 $end
$var wire 1 5! w2 $end
$var wire 1 6! w3 $end

$scope module x1 $end
$var wire 1 H in1 $end
$var wire 1 X in2 $end
$var wire 1 4! out $end
$upscope $end

$scope module x2 $end
$var wire 1 4! in1 $end
$var wire 1 /! in2 $end
$var wire 1 1 out $end
$upscope $end

$scope module na1 $end
$var wire 1 H in1 $end
$var wire 1 X in2 $end
$var wire 1 5! out $end
$upscope $end

$scope module na2 $end
$var wire 1 /! in1 $end
$var wire 1 4! in2 $end
$var wire 1 6! out $end
$upscope $end

$scope module na3 $end
$var wire 1 6! in1 $end
$var wire 1 5! in2 $end
$var wire 1 0! out $end
$upscope $end
$upscope $end

$scope module fa1 $end
$var wire 1 I A $end
$var wire 1 Y B $end
$var wire 1 .! Cin $end
$var wire 1 2 S $end
$var wire 1 /! Cout $end
$var wire 1 7! w1 $end
$var wire 1 8! w2 $end
$var wire 1 9! w3 $end

$scope module x1 $end
$var wire 1 I in1 $end
$var wire 1 Y in2 $end
$var wire 1 7! out $end
$upscope $end

$scope module x2 $end
$var wire 1 7! in1 $end
$var wire 1 .! in2 $end
$var wire 1 2 out $end
$upscope $end

$scope module na1 $end
$var wire 1 I in1 $end
$var wire 1 Y in2 $end
$var wire 1 8! out $end
$upscope $end

$scope module na2 $end
$var wire 1 .! in1 $end
$var wire 1 7! in2 $end
$var wire 1 9! out $end
$upscope $end

$scope module na3 $end
$var wire 1 9! in1 $end
$var wire 1 8! in2 $end
$var wire 1 /! out $end
$upscope $end
$upscope $end

$scope module fa0 $end
$var wire 1 J A $end
$var wire 1 Z B $end
$var wire 1 -! Cin $end
$var wire 1 3 S $end
$var wire 1 .! Cout $end
$var wire 1 :! w1 $end
$var wire 1 ;! w2 $end
$var wire 1 <! w3 $end

$scope module x1 $end
$var wire 1 J in1 $end
$var wire 1 Z in2 $end
$var wire 1 :! out $end
$upscope $end

$scope module x2 $end
$var wire 1 :! in1 $end
$var wire 1 -! in2 $end
$var wire 1 3 out $end
$upscope $end

$scope module na1 $end
$var wire 1 J in1 $end
$var wire 1 Z in2 $end
$var wire 1 ;! out $end
$upscope $end

$scope module na2 $end
$var wire 1 -! in1 $end
$var wire 1 :! in2 $end
$var wire 1 <! out $end
$upscope $end

$scope module na3 $end
$var wire 1 <! in1 $end
$var wire 1 ;! in2 $end
$var wire 1 .! out $end
$upscope $end
$upscope $end
$upscope $end
$upscope $end
$upscope $end
$enddefinitions $end
#0
$dumpvars
b11010100100100 !
b101111010000001 "
bx #
18
19
b1 :
13
02
11
00
0/
1.
0-
1,
1+
1*
0)
0(
1'
0&
0%
1$
04
15
16
z7
0[
0\
1]
1^
1_
1`
0a
1b
1c
1d
1e
0f
1g
1h
0i
0j
0k
1l
0m
0n
1o
1p
1q
0r
0s
0t
1u
1v
1w
1x
1y
1z
1{
0|
0}
0~
1!!
1"!
1#!
0$!
1%!
1&!
1'!
1(!
1)!
0*!
1+!
1,!
0.!
0/!
00!
01!
12!
13!
14!
15!
16!
07!
18!
19!
1:!
1;!
1<!
1Z
0Y
0X
0W
0V
0U
0T
1S
0R
1Q
1P
1O
1N
0M
1L
0K
0J
0I
1H
0G
0F
1E
0D
0C
1B
0A
1@
0?
1>
1=
0<
0;
0-!
$end
#50
08
05
b1001001110100101 #
#100
18
15
b1101011000001001 !
b101011001100011 "
b10 :
1Y
1U
1T
0S
0O
1J
0H
1G
0E
0B
1A
0=
1<
1;
1a
0d
0e
0g
0v
0w
0y
11!
04!
0:!
0;!
0p
0!!
1$!
17!
12
1-
0,
1(
1r
1.!
03
01
10
0+
1n
0*
1&
1i
1%
1f
0$
0c
14
0_
1)
02
09!
0]
0'
1/!
0%
11
#150
08
05
b10010110001101100 #
#200
18
15
b111101100001101 !
b1001100110001101 "
b11 :
0Y
1X
1W
0U
0T
1S
1R
0Q
0P
1O
0L
1K
1H
1B
0@
1?
1=
0;
1g
0q
0z
05!
1d
1e
1t
1v
1w
1!!
0$!
0'!
01!
02!
07!
12
19!
1[
00
0.
0-
1,
0n
1*
0o
0`
1%
10!
1m
1]
0&
0i
1_
1'
0*
0x
10
1$
1c
0(
0)
1/
0/!
01
04
1n
0%
0f
1`
1)
0$
0c
14
#201
09
06
#250
08
05
b10001010010011010 #
#300
18
15
b1000010001100101 !
b101001000010010 "
b100 :
0Z
1Y
0X
0W
1V
0S
0R
1Q
0O
1L
0K
0G
1E
1D
0B
0A
1@
0?
0>
0=
0<
1;
0g
1j
1k
1s
1$!
1'!
1q
1z
0!!
1*!
12!
14!
15!
17!
1:!
1;!
0.!
13
00!
11
0[
0,
0m
0]
1.
1-
0)
0u
0^
1i
0_
1o
1*
1x
00
0n
1(
1%
1f
0`
1)
1u
0o
1$
1c
04
0(
#350
08
05
b1101011001110111 #
#400
18
15
b1110001100000001 !
b1100110100001101 "
b101 :
1Z
0Y
1X
1W
0V
1R
0Q
1P
1O
0N
1K
0H
0E
0D
1B
1A
0@
1=
1<
0d
0e
1g
0z
0$!
0'!
0a
0b
0j
1p
0*!
11!
07!
0:!
0;!
1.!
03
10
0/
1(
0'
14
0$
0.
0-
1m
1&
1`
0%
1$
0*
0x
1n
0)
0u
1o
0(
0r
1]
1'
#450
08
05
b11011000000001110 #
#500
18
15
b1111000101110110 !
b1100110100111101 "
b110 :
1V
1U
0J
1I
1H
1F
1E
1D
0A
1>
1j
0v
1$!
0(!
0+!
04!
05!
17!
1:!
1;!
0.!
13
10!
01
1|
1}
1*
1x
0'
0l
1^
0n
0&!
1.
00
03!
1[
1~
1)
1u
0&
0i
1_
0o
1,
1/
1(
1r
1%
0]
1'
1l
0^
1&
1i
0_
0%
#550
08
05
b11011111010110011 #
#600
18
15
b101011111101101 !
b1111011110001100 "
b111 :
0Z
0V
0U
1S
1Q
0O
1N
1M
1J
0I
1G
0F
1C
1A
1@
0=
0;
1a
1b
0s
0t
0w
0"!
01!
02!
07!
0j
0k
0p
1'!
1(!
1+!
0|
0}
0(
1^
0'
02
10
13!
1\
1n
1o
04
0$
0c
14
1(
1+
0&
0i
1-
1&!
0~
1_
1%
0,
#650
08
05
b10100111101111001 #
#700
18
15
b1110100111111001 !
b10010011000110 "
b1000 :
1Y
0W
1T
0R
0Q
0N
0L
0K
0H
1F
0A
0@
1?
0>
1=
1;
0g
0h
1p
1s
1t
1*!
14!
15!
1d
1e
1k
1w
1y
1z
0$!
0%!
11!
12!
17!
12
0[
00
03!
1~
0-
0m
0+
0{
0n
0^
0`
0%
0f
00!
11
0o
1i
10
13!
1`
1m
1,
#750
08
05
b10000111010111111 #
#800
18
15
b1000010011000101 !
b1101001010101010 "
b1001 :
0X
1W
1U
0T
1Q
0P
1N
0M
1L
1K
1H
0G
0F
0E
0B
1@
0?
0=
0<
0p
0y
0*!
0a
0b
1h
1j
1v
1$!
1%!
0~
1-
0*
0x
1'
0_
1$
1c
0/
1+
1{
0(
0m
1%
1f
1n
0,
0)
0u
0`
1*
1x
0n
0$
1o
1(
1)
1u
0o
0(
#850
08
05
b10101011101101111 #
#900
18
15
b1111011111100101 !
b111001001110111 "
b1010 :
1Z
1X
0W
1V
1T
0S
1M
0K
1E
1B
1A
1>
1=
1<
0d
0e
0h
0j
0k
0v
0w
1y
0'!
0(!
1a
1b
1!!
1"!
0$!
0%!
1*!
01!
04!
05!
0:!
0;!
1.!
03
10!
01
1/
1~
0-
0\
04
1$
1}
0.
1n
0*
1^
0'
1_
1`
0$
0c
1&
0)
0u
1-
0#!
02
09!
1/!
1\
1o
14
1(
0+
0{
11
1m
1*
#950
08
05
b10110101001011100 #
#1000
18
15
b1101011000010010 !
b1101101110001111 "
b1011 :
1W
0V
0U
0T
1S
1R
1O
0M
1K
0J
1I
0H
1F
0E
0D
0C
0B
0=
14!
15!
07!
08!
1:!
1;!
0a
0b
1h
1p
1%!
1(!
11!
00
03!
0}
0~
0(
0r
0_
1$
1c
0.!
13
19!
00!
01
06!
10!
0%
1]
1,
1#!
0-
1[
0/
0,!
0\
1'
1+
1{
1|
1.
0m
0*
#1050
08
05
b11011000110100001 #
#1100
18
15
b110100111110010 !
b1001011011001110 "
b1100 :
0Z
1T
0R
1P
0O
0L
1E
1D
1C
1B
0A
0@
1?
0>
1=
0;
1a
1b
1g
1j
1k
1v
1w
0!!
0"!
0%!
1'!
1d
1e
0:!
03
0`
1%
0.
0)!
1~
1\
0n
1*
0^
0'
0l
04
1^
1)
1u
0+
0{
1}
1-
1m
0o
0&
0i
1_
1(
1r
0*
0x
1n
0]
0%
0f
1`
1'
1l
0)
0u
1o
0^
0$
0c
14
1&
1i
0(
0r
1]
0_
1%
1f
0'
0l
1^
0`
1$
1c
0&
0i
1_
04
0%
0f
1`
0$
0c
14
#1150
08
05
b10000000011000000 #
#1200
18
15
b111101011101000 !
b100111011000101 "
b1101 :
1Z
0Y
0W
1O
0N
1L
0K
0I
1G
0F
0B
1A
1>
0v
0w
0y
0*!
0a
0d
0e
0p
0q
18!
1:!
13
0/!
1(
1r
1%
1f
1$
1c
1/
1,!
1+
1{
1*
1x
0m
0|
04
11
16!
00!
1.
1)!
0*
0}
10
13!
0[
0-
0/
#1250
08
05
b1100100110101101 #
#1300
18
15
b100100101011100 !
b10100010111101 "
b1110 :
1W
1V
1U
0T
0Q
0P
1M
0L
1H
1F
0E
0C
1B
0A
0>
0=
0j
1y
1!!
1"!
0+!
04!
05!
1d
1e
0s
1w
1$!
1%!
01!
02!
1[
00
0~
1-
0n
1u
0`
0%
0f
10!
01
1|
0\
1'
1l
0^
0.
0)!
10
1`
0o
1/
0(
1}
1&
1i
0_
0-
0&!
1~
1%
1f
0`
0,
0#!
1\
0$
0+
0{
1m
1*
#1350
08
05
b111001000011001 #
