hw1/hw1_2/nand2.v
module nand2 (in1,in2,out);
input in1,in2;
output out;
assign out = ~(in1 & in2);
endmodule

hw1/hw1_1/not1.v
module not1 (in1,out);
input in1;
output out;
assign out = ~in1;
endmodule

hw2/hw2_1/mux2_1.v
module mux2_1(InA, InB, S, Out);

  input InA, InB, S;
  output Out;
  wire w1, w2, wNS;
  
  // mux implementation
  // S = 0 will choose InA, S = 1 will choose InB
  nand2 na1 (.in1(InB), .in2(S), .out(w1));
  not1 n1 (.in1(S), .out(wNS));
  nand2 na2 (.in1(InA), .in2(wNS), .out(w2));
  nand2 na3(.in1(w1), .in2(w2), .out(Out));
endmodule

hw1/hw1_1/mux4_1.v
module mux4_1(InA, InB, InC, InD, S, Out);

  input InA, InB, InC, InD;
  input [1:0] S;
  output Out;
  wire out1, out2;
  
  //s = 1, out1 = InB out2 = InD, s = 0, out1 = InA out2 = InC
  mux2_1 mux1 (.InA(InA), .InB(InB), .S(S[0]), .Out(out1));
  mux2_1 mux2 (.InA(InC), .InB(InD), .S(S[0]), .Out(out2));
  //choose lower or upper section based on s
  mux2_1 mux3 (.InA(out1), .InB(out2), .S(S[1]), .Out(Out));

endmodule

demo2/verilog/quadmux4_1.v
module quadmux4_1(InA, InB, InC, InD, S, Out);

  input [3:0] InA, InB, InC, InD;
  input [1:0] S;
  output [3:0] Out;
  
  //make 4 muxes, then concatenate each bit at the end
  mux4_1 m3(InA[3], InB[3], InC[3], InD[3], S, Out[3]);
  mux4_1 m2(InA[2], InB[2], InC[2], InD[2], S, Out[2]);
  mux4_1 m1(InA[1], InB[1], InC[1], InD[1], S, Out[1]);
  mux4_1 m0(InA[0], InB[0], InC[0], InD[0], S, Out[0]);

endmodule

hw2/hw2_1/clkrst.v
/* $Author: karu $ */
/* $LastChangedDate: 2009-03-04 23:09:45 -0600 (Wed, 04 Mar 2009) $ */
/* $Rev: 45 $ */
// clock and reset generator
// CS/ECE 552
// Andy Phelps (TA)
// 3/22/06

// Clock period is 100 time units, and reset length
// to 201 time units (two rising edges of clock).

module clkrst (clk, rst, err);

    output clk;
    output rst;
    input  err;

    reg clk;
    reg rst;
    integer cycle_count;

    initial begin
      $dumpvars;
      cycle_count = 0;
      rst = 1;
      clk = 1;
      #201 rst = 0; // delay until slightly after two clock periods
    end

    always #50 begin   // delay 1/2 clock period each time thru loop
      clk = ~clk;
      if (clk & err) begin
        $display("Error signal asserted");
        $stop;
      end
    end

    always @(posedge clk) begin
    	cycle_count = cycle_count + 1;
	if (cycle_count > 100000) begin
		$display("hmm....more than 100000 cycles of simulation...error?\n");
		$finish;
	end
    end


endmodule
// DUMMY LINE FOR REV CONTROL :0:

hw1/hw1_1/quadmux4_1_bench.v
module quadmux4_1_bench;

      // No inputs and outputs : testbenchs just a wrapper.

      // reg/wire definitions, we'll use these to drive our inputs and capture our outputs
   reg [3:0] InA;

   reg [3:0] InB;

   reg [3:0] InC;

   reg [3:0] InD;

   reg [1:0] S;

   wire [3:0] Out;

   wire Clk;
   //2 dummy wires
   wire rst;
   wire err;

//clkrst module instantiation
clkrst my_clkrst( .clk(Clk), .rst(rst), .err(err));

      // Module instantiation :
   quadmux4_1 DUT (.InA(InA), .InB(InB),.InC(InC),.InD(InD), .S(S), .Out(Out));

      // Input drivers :
      //  Check every combination of S

      // Whatever you put within an initial block will be executed
      // when simulation starts
   initial
     begin
	     // Lets initialize all inputs (We dont want any 'Z's)
	InA = 4'b0001;
	InB = 4'b1000;
	InC = 4'b1010;
	InD = 4'b0101;
        S = 2'b00;
	         // #10 means wait for a delay of 10 ticks.
	         // By doing this we hold every singal for some time, which allows
	         // for the combinational logical delay and for the output to be computed
	
	
	#3200    $finish;
	

     end // initial begin
      // The test is not complete (we didnt check every combination of all inputs, InA for example. But we can be pretty confident if this much works.

//Random values 
always@(posedge Clk) 
     begin
        InA = $random;
	InB = $random;
	InC = $random;
	InD = $random;
        S = $random;
     end

//always@(posedge Clk) S = S + 1;
// Output monitors
   always@(negedge Clk)
       // Sensitivity list ^^^ tells Modelsim what this always block is "sensitive" to.
       // Try to figure out what happens if you didnt include lets say InC...
           // Whenever any of these signals change, this block will execute
     begin
	case (S)
	    // This is a behavior description of what the mux is supposed to do...
	    // For every combination of S :
	  2'b00 : 
	    if (Out !== InA) $display ("ERRORCHECK InA S=0");
	  2'b01 : 
	    if (Out !== InB) $display ("ERRORCHECK InB S=1");  
	  2'b10 :
	    if (Out !== InC) $display ("ERRORCHECK InC S=2");
	  2'b11 : 
	    if (Out !== InD) $display ("ERRORCHECK InD S=3");
	  
	endcase // case (S)
     end // always@ (S, InA, InB, InC, InD, Out)

   endmodule // End of module : tb_quadmux4to1

hw1/hw1_1/dump.vcd
$date
	Mon Sep 21 13:05:04 2020
$end
$version
	ModelSim Version 10.7c
$end
$timescale
	1ns
$end

$scope module quadmux4_1_bench $end
$var reg 4 ! InA [3:0] $end
$var reg 4 " InB [3:0] $end
$var reg 4 # InC [3:0] $end
$var reg 4 $ InD [3:0] $end
$var reg 2 % S [1:0] $end
$var wire 1 & Out [3] $end
$var wire 1 ' Out [2] $end
$var wire 1 ( Out [1] $end
$var wire 1 ) Out [0] $end
$var wire 1 * Clk $end
$var wire 1 + rst $end
$var wire 1 , err $end

$scope module my_clkrst $end
$var reg 1 - clk $end
$var reg 1 . rst $end
$var wire 1 , err $end
$var integer 32 / cycle_count $end
$upscope $end

$scope module DUT $end
$var wire 1 0 InA [3] $end
$var wire 1 1 InA [2] $end
$var wire 1 2 InA [1] $end
$var wire 1 3 InA [0] $end
$var wire 1 4 InB [3] $end
$var wire 1 5 InB [2] $end
$var wire 1 6 InB [1] $end
$var wire 1 7 InB [0] $end
$var wire 1 8 InC [3] $end
$var wire 1 9 InC [2] $end
$var wire 1 : InC [1] $end
$var wire 1 ; InC [0] $end
$var wire 1 < InD [3] $end
$var wire 1 = InD [2] $end
$var wire 1 > InD [1] $end
$var wire 1 ? InD [0] $end
$var wire 1 @ S [1] $end
$var wire 1 A S [0] $end
$var wire 1 & Out [3] $end
$var wire 1 ' Out [2] $end
$var wire 1 ( Out [1] $end
$var wire 1 ) Out [0] $end

$scope module m3 $end
$var wire 1 0 InA $end
$var wire 1 4 InB $end
$var wire 1 8 InC $end
$var wire 1 < InD $end
$var wire 1 @ S [1] $end
$var wire 1 A S [0] $end
$var wire 1 & Out $end
$var wire 1 B out1 $end
$var wire 1 C out2 $end

$scope module mux1 $end
$var wire 1 0 InA $end
$var wire 1 4 InB $end
$var wire 1 A S $end
$var wire 1 B Out $end
$var wire 1 D w1 $end
$var wire 1 E w2 $end
$var wire 1 F wNS $end

$scope module na1 $end
$var wire 1 4 in1 $end
$var wire 1 A in2 $end
$var wire 1 D out $end
$upscope $end

$scope module n1 $end
$var wire 1 A in1 $end
$var wire 1 F out $end
$upscope $end

$scope module na2 $end
$var wire 1 0 in1 $end
$var wire 1 F in2 $end
$var wire 1 E out $end
$upscope $end

$scope module na3 $end
$var wire 1 D in1 $end
$var wire 1 E in2 $end
$var wire 1 B out $end
$upscope $end
$upscope $end

$scope module mux2 $end
$var wire 1 8 InA $end
$var wire 1 < InB $end
$var wire 1 A S $end
$var wire 1 C Out $end
$var wire 1 G w1 $end
$var wire 1 H w2 $end
$var wire 1 I wNS $end

$scope module na1 $end
$var wire 1 < in1 $end
$var wire 1 A in2 $end
$var wire 1 G out $end
$upscope $end

$scope module n1 $end
$var wire 1 A in1 $end
$var wire 1 I out $end
$upscope $end

$scope module na2 $end
$var wire 1 8 in1 $end
$var wire 1 I in2 $end
$var wire 1 H out $end
$upscope $end

$scope module na3 $end
$var wire 1 G in1 $end
$var wire 1 H in2 $end
$var wire 1 C out $end
$upscope $end
$upscope $end

$scope module mux3 $end
$var wire 1 B InA $end
$var wire 1 C InB $end
$var wire 1 @ S $end
$var wire 1 & Out $end
$var wire 1 J w1 $end
$var wire 1 K w2 $end
$var wire 1 L wNS $end

$scope module na1 $end
$var wire 1 C in1 $end
$var wire 1 @ in2 $end
$var wire 1 J out $end
$upscope $end

$scope module n1 $end
$var wire 1 @ in1 $end
$var wire 1 L out $end
$upscope $end

$scope module na2 $end
$var wire 1 B in1 $end
$var wire 1 L in2 $end
$var wire 1 K out $end
$upscope $end

$scope module na3 $end
$var wire 1 J in1 $end
$var wire 1 K in2 $end
$var wire 1 & out $end
$upscope $end
$upscope $end
$upscope $end

$scope module m2 $end
$var wire 1 1 InA $end
$var wire 1 5 InB $end
$var wire 1 9 InC $end
$var wire 1 = InD $end
$var wire 1 @ S [1] $end
$var wire 1 A S [0] $end
$var wire 1 ' Out $end
$var wire 1 M out1 $end
$var wire 1 N out2 $end

$scope module mux1 $end
$var wire 1 1 InA $end
$var wire 1 5 InB $end
$var wire 1 A S $end
$var wire 1 M Out $end
$var wire 1 O w1 $end
$var wire 1 P w2 $end
$var wire 1 Q wNS $end

$scope module na1 $end
$var wire 1 5 in1 $end
$var wire 1 A in2 $end
$var wire 1 O out $end
$upscope $end

$scope module n1 $end
$var wire 1 A in1 $end
$var wire 1 Q out $end
$upscope $end

$scope module na2 $end
$var wire 1 1 in1 $end
$var wire 1 Q in2 $end
$var wire 1 P out $end
$upscope $end

$scope module na3 $end
$var wire 1 O in1 $end
$var wire 1 P in2 $end
$var wire 1 M out $end
$upscope $end
$upscope $end

$scope module mux2 $end
$var wire 1 9 InA $end
$var wire 1 = InB $end
$var wire 1 A S $end
$var wire 1 N Out $end
$var wire 1 R w1 $end
$var wire 1 S w2 $end
$var wire 1 T wNS $end

$scope module na1 $end
$var wire 1 = in1 $end
$var wire 1 A in2 $end
$var wire 1 R out $end
$upscope $end

$scope module n1 $end
$var wire 1 A in1 $end
$var wire 1 T out $end
$upscope $end

$scope module na2 $end
$var wire 1 9 in1 $end
$var wire 1 T in2 $end
$var wire 1 S out $end
$upscope $end

$scope module na3 $end
$var wire 1 R in1 $end
$var wire 1 S in2 $end
$var wire 1 N out $end
$upscope $end
$upscope $end

$scope module mux3 $end
$var wire 1 M InA $end
$var wire 1 N InB $end
$var wire 1 @ S $end
$var wire 1 ' Out $end
$var wire 1 U w1 $end
$var wire 1 V w2 $end
$var wire 1 W wNS $end

$scope module na1 $end
$var wire 1 N in1 $end
$var wire 1 @ in2 $end
$var wire 1 U out $end
$upscope $end

$scope module n1 $end
$var wire 1 @ in1 $end
$var wire 1 W out $end
$upscope $end

$scope module na2 $end
$var wire 1 M in1 $end
$var wire 1 W in2 $end
$var wire 1 V out $end
$upscope $end

$scope module na3 $end
$var wire 1 U in1 $end
$var wire 1 V in2 $end
$var wire 1 ' out $end
$upscope $end
$upscope $end
$upscope $end

$scope module m1 $end
$var wire 1 2 InA $end
$var wire 1 6 InB $end
$var wire 1 : InC $end
$var wire 1 > InD $end
$var wire 1 @ S [1] $end
$var wire 1 A S [0] $end
$var wire 1 ( Out $end
$var wire 1 X out1 $end
$var wire 1 Y out2 $end

$scope module mux1 $end
$var wire 1 2 InA $end
$var wire 1 6 InB $end
$var wire 1 A S $end
$var wire 1 X Out $end
$var wire 1 Z w1 $end
$var wire 1 [ w2 $end
$var wire 1 \ wNS $end

$scope module na1 $end
$var wire 1 6 in1 $end
$var wire 1 A in2 $end
$var wire 1 Z out $end
$upscope $end

$scope module n1 $end
$var wire 1 A in1 $end
$var wire 1 \ out $end
$upscope $end

$scope module na2 $end
$var wire 1 2 in1 $end
$var wire 1 \ in2 $end
$var wire 1 [ out $end
$upscope $end

$scope module na3 $end
$var wire 1 Z in1 $end
$var wire 1 [ in2 $end
$var wire 1 X out $end
$upscope $end
$upscope $end

$scope module mux2 $end
$var wire 1 : InA $end
$var wire 1 > InB $end
$var wire 1 A S $end
$var wire 1 Y Out $end
$var wire 1 ] w1 $end
$var wire 1 ^ w2 $end
$var wire 1 _ wNS $end

$scope module na1 $end
$var wire 1 > in1 $end
$var wire 1 A in2 $end
$var wire 1 ] out $end
$upscope $end

$scope module n1 $end
$var wire 1 A in1 $end
$var wire 1 _ out $end
$upscope $end

$scope module na2 $end
$var wire 1 : in1 $end
$var wire 1 _ in2 $end
$var wire 1 ^ out $end
$upscope $end

$scope module na3 $end
$var wire 1 ] in1 $end
$var wire 1 ^ in2 $end
$var wire 1 Y out $end
$upscope $end
$upscope $end

$scope module mux3 $end
$var wire 1 X InA $end
$var wire 1 Y InB $end
$var wire 1 @ S $end
$var wire 1 ( Out $end
$var wire 1 ` w1 $end
$var wire 1 a w2 $end
$var wire 1 b wNS $end

$scope module na1 $end
$var wire 1 Y in1 $end
$var wire 1 @ in2 $end
$var wire 1 ` out $end
$upscope $end

$scope module n1 $end
$var wire 1 @ in1 $end
$var wire 1 b out $end
$upscope $end

$scope module na2 $end
$var wire 1 X in1 $end
$var wire 1 b in2 $end
$var wire 1 a out $end
$upscope $end

$scope module na3 $end
$var wire 1 ` in1 $end
$var wire 1 a in2 $end
$var wire 1 ( out $end
$upscope $end
$upscope $end
$upscope $end

$scope module m0 $end
$var wire 1 3 InA $end
$var wire 1 7 InB $end
$var wire 1 ; InC $end
$var wire 1 ? InD $end
$var wire 1 @ S [1] $end
$var wire 1 A S [0] $end
$var wire 1 ) Out $end
$var wire 1 c out1 $end
$var wire 1 d out2 $end

$scope module mux1 $end
$var wire 1 3 InA $end
$var wire 1 7 InB $end
$var wire 1 A S $end
$var wire 1 c Out $end
$var wire 1 e w1 $end
$var wire 1 f w2 $end
$var wire 1 g wNS $end

$scope module na1 $end
$var wire 1 7 in1 $end
$var wire 1 A in2 $end
$var wire 1 e out $end
$upscope $end

$scope module n1 $end
$var wire 1 A in1 $end
$var wire 1 g out $end
$upscope $end

$scope module na2 $end
$var wire 1 3 in1 $end
$var wire 1 g in2 $end
$var wire 1 f out $end
$upscope $end

$scope module na3 $end
$var wire 1 e in1 $end
$var wire 1 f in2 $end
$var wire 1 c out $end
$upscope $end
$upscope $end

$scope module mux2 $end
$var wire 1 ; InA $end
$var wire 1 ? InB $end
$var wire 1 A S $end
$var wire 1 d Out $end
$var wire 1 h w1 $end
$var wire 1 i w2 $end
$var wire 1 j wNS $end

$scope module na1 $end
$var wire 1 ? in1 $end
$var wire 1 A in2 $end
$var wire 1 h out $end
$upscope $end

$scope module n1 $end
$var wire 1 A in1 $end
$var wire 1 j out $end
$upscope $end

$scope module na2 $end
$var wire 1 ; in1 $end
$var wire 1 j in2 $end
$var wire 1 i out $end
$upscope $end

$scope module na3 $end
$var wire 1 h in1 $end
$var wire 1 i in2 $end
$var wire 1 d out $end
$upscope $end
$upscope $end

$scope module mux3 $end
$var wire 1 c InA $end
$var wire 1 d InB $end
$var wire 1 @ S $end
$var wire 1 ) Out $end
$var wire 1 k w1 $end
$var wire 1 l w2 $end
$var wire 1 m wNS $end

$scope module na1 $end
$var wire 1 d in1 $end
$var wire 1 @ in2 $end
$var wire 1 k out $end
$upscope $end

$scope module n1 $end
$var wire 1 @ in1 $end
$var wire 1 m out $end
$upscope $end

$scope module na2 $end
$var wire 1 c in1 $end
$var wire 1 m in2 $end
$var wire 1 l out $end
$upscope $end

$scope module na3 $end
$var wire 1 k in1 $end
$var wire 1 l in2 $end
$var wire 1 ) out $end
$upscope $end
$upscope $end
$upscope $end
$upscope $end
$upscope $end
$enddefinitions $end
#0
$dumpvars
b100 !
b1 "
b1001 #
b11 $
b1 %
1-
1.
b1 /
1)
0(
0'
0&
1*
1+
z,
0B
0C
1D
1E
0F
1G
1H
0I
1J
1K
1L
0M
0N
1O
1P
0Q
1R
1S
0T
1U
1V
1W
0X
1Y
1Z
1[
0\
0]
1^
0_
1`
1a
1b
1c
1d
0e
1f
0g
0h
1i
0j
1k
0l
1m
1A
0@
1?
1>
0=
0<
1;
0:
09
18
17
06
05
04
03
02
11
00
$end
#50
0-
0*
#100
1-
1*
b1101 !
b101 "
b10 #
b1 $
b10 /
0>
0;
1:
08
15
13
10
0O
1]
0Y
1M
0V
1'
#150
0-
0*
#200
1-
1*
b110 !
b1101 "
b1101 #
b1100 $
b11 /
0?
1=
1<
1;
0:
19
18
14
03
12
00
0D
0G
0R
1h
0d
1N
1C
1B
0K
1&
#201
0.
0+
#250
0-
0*
#300
1-
1*
b101 "
b1010 #
b101 $
b11 %
b100 /
1@
1?
0<
0;
1:
09
04
1D
1G
0h
0J
0L
0U
0W
0b
0m
1l
1V
1K
1d
0C
0B
1J
0k
0&
#350
0-
0*
#400
1-
1*
b10 !
b1111 "
b10 #
b1110 $
b0 %
b101 /
0A
0@
0?
1>
1<
08
16
14
01
1L
1U
1W
1b
1k
1m
1F
1I
1O
1Q
1R
1T
1\
1_
1e
1g
1h
1j
0d
0c
0^
0[
0N
0M
0)
0'
1X
1Y
0a
1(
#450
0-
0*
#500
1-
1*
b101 !
b1100 "
b1101 #
b1101 $
b1 %
b110 /
1A
1?
0>
1;
0:
19
18
07
06
13
02
11
0P
1[
0f
0H
0S
1^
0i
0h
0D
0F
0G
0I
0O
0Q
0R
0T
0\
0_
0g
0j
1i
1f
1S
1P
1H
1B
1d
0Y
1N
1C
0X
1M
0V
1a
0K
1&
0(
1'
#550
0-
0*
#600
1-
1*
b11 !
b1010 "
b0 #
b0 $
b10 %
b111 /
0A
1@
0?
0=
0<
0;
09
08
16
05
12
01
0J
0L
0U
0W
0b
0k
0m
1D
1F
1G
1I
1O
1Q
1R
1T
1\
1_
1g
1h
1j
0d
0f
0[
0N
0M
0C
0B
1)
1V
1K
1J
1U
1X
1c
1k
0)
0'
0&
#650
0-
0*
#700
1-
1*
b1101 !
b110 "
b11 #
b1101 $
b11 %
b1000 /
1A
1?
1=
1<
1;
1:
15
04
02
11
10
0E
0P
1[
0O
0^
0i
0G
0R
0h
0F
0I
0Q
0T
0Z
0\
0_
0g
0j
1i
1f
1^
1P
1E
1N
1C
1d
1M
0k
0J
0U
0c
1'
1&
1)
#750
0-
0*
#800
1-
1*
b1011 !
b101 "
b10 #
b1110 $
b1 %
b1001 /
0@
0?
1>
0;
17
06
12
01
1Z
0e
0]
1h
1J
1L
1U
1W
1b
1k
1m
0)
0a
0V
0&
0d
1Y
1c
0X
1a
0l
1)
#850
0-
0*
#900
1-
1*
b1111 !
b11 "
b1010 #
b1010 $
b0 %
b1010 /
0A
0=
18
16
05
11
1F
1G
1I
1O
1Q
1R
1T
1\
1]
1_
1e
1g
1j
0f
0^
0[
0N
0P
0H
0E
1B
1X
0a
0K
1&
1(
#950
0-
0*
#1000
1-
1*
b10 !
b1010 "
b1 #
b1000 $
b1011 /
0>
1;
0:
08
07
14
03
01
00
1E
1P
1f
1H
1^
0i
1d
0Y
0C
0c
0M
0B
1K
1V
1l
0)
0'
0&
#1050
0-
0*
#1100
1-
1*
b1001 !
b1011 "
b110 #
b110 $
b10 %
b1100 /
1@
1>
1=
0<
0;
1:
19
17
13
02
10
0E
1[
0f
0S
0^
1i
0L
0W
0b
0k
0m
1)
1a
0d
1Y
1N
1c
0X
1B
0U
0`
1k
0)
1'
#1150
0-
0*
#1200
1-
1*
b1100 !
b1010 "
b1011 #
b1 $
b1 %
b1101 /
1A
0@
1?
0>
0=
1;
09
18
07
03
11
0P
1f
0H
1S
0i
0h
1L
1U
1W
1`
1b
1m
0D
0F
0I
0Q
0T
0Z
0\
0_
0g
0j
1i
1^
1X
1P
1H
1E
0l
0(
0'
0K
1d
0N
0c
1l
1&
0a
0Y
1(
#1250
0-
0*
#1300
1-
1*
b1111 !
b1011 "
b1010 #
b1110 $
b1110 /
0?
1>
1=
1<
0;
17
13
12
0e
0G
0R
0]
1h
0d
1Y
1N
1C
1c
0l
1)
#1350
0-
0*
#1400
1-
1*
b1 !
b1001 "
b10 #
b1100 $
b11 %
b1111 /
1@
0>
08
06
02
01
00
1Z
1]
0J
0L
0U
0W
0`
0b
0m
1l
1a
1'
1K
0Y
0X
1`
0)
0(
#1450
0-
0*
#1500
1-
1*
b1111 !
b1000 "
b111 #
b1111 $
b0 %
b10000 /
0A
0@
1?
1>
1;
19
07
12
11
10
1J
1L
1U
1W
1b
1m
1D
1F
1G
1I
1Q
1R
1T
1\
1_
1e
1g
1j
0i
0f
0^
0[
0S
0P
0C
0E
0l
0'
0K
1)
1M
1X
1Y
1d
0a
0V
1'
1(
#1550
0-
0*
#1600
1-
1*
b1011 !
b1001 "
b1001 #
b0 $
b11 %
b10001 /
1A
1@
0?
0>
0=
0<
0:
09
18
17
01
1P
0e
0H
1S
1^
0L
0U
0W
0`
0b
0k
0m
0D
0F
0I
0Q
0T
0\
0_
0g
0j
1i
1f
1[
1H
1E
1l
1a
1V
1K
0Y
0N
0M
1U
1`
0&
0X
0d
1k
0(
0'
0)
#1650
0-
0*
#1700
1-
1*
b1 !
b110 "
b1100 #
b10 $
b0 %
b10010 /
0A
0@
1>
0;
19
07
16
15
04
02
00
1L
1W
1b
1m
1D
1F
1I
1Q
1T
1\
1_
1e
1g
1j
0f
0S
0H
0B
0l
1)
1C
1N
#1750
0-
0*
#1800
1-
1*
b111 !
b1101 "
b10 #
b1110 $
b1 %
b10011 /
1A
1=
1<
1:
09
08
17
06
14
12
11
0P
0[
0D
0e
1H
1S
0^
0G
0R
0F
0I
0O
0Q
0T
0\
0]
0_
0g
0j
1f
1^
1[
1P
1Y
1B
1M
0V
0K
1&
1'
#1850
0-
0*
#1900
1-
1*
b1001 !
b1111 "
b11 #
b101 $
b0 %
b10100 /
0A
1?
0>
0<
1;
16
02
01
10
1D
1F
1G
1I
1O
1Q
1R
1T
1\
1]
1_
1e
1g
1j
0i
0f
0^
0N
0M
0C
0E
1V
1d
0'
#1950
0-
0*
#2000
1-
1*
b1011 !
b1001 "
b1111 #
b1010 $
b10101 /
0?
1>
0=
1<
19
18
06
05
12
0[
0H
0S
1N
1C
1X
0a
1(
#2050
0-
0*
#2100
1-
1*
b110 !
b1110 "
b1100 #
b10 %
b10110 /
1@
0;
0:
07
16
15
03
11
00
1E
0P
1f
1^
1i
0J
0L
0U
0W
0`
0b
0k
0m
1l
1a
1'
1K
0d
0Y
0c
1M
0B
1`
1k
0)
0(
#2150
0-
0*
#2200
1-
1*
b11 !
b11 "
b1111 #
b11 $
b11 %
b10111 /
1A
1?
0<
1;
1:
17
05
04
13
01
1P
0f
0e
0^
0i
0h
0F
0I
0Q
0T
0Z
0\
0]
0_
0g
0j
1i
1f
1^
1[
1S
1H
1d
1Y
1c
0M
0`
0k
0C
0N
1U
1J
1)
1(
0&
0'
#2250
0-
0*
#2300
1-
1*
b100 !
b111 "
b1011 #
b110 $
b10 %
b11000 /
0A
0?
1=
09
15
03
02
11
1F
1I
1Q
1T
1Z
1\
1]
1_
1e
1g
1h
1j
0i
0c
0^
0X
0P
0H
1C
1M
0J
1&
#2350
0-
0*
#2400
1-
1*
b1001 !
b1101 "
b1010 #
b101 $
b1 %
b11001 /
1A
0@
1?
0>
0;
06
14
13
01
10
0E
1P
0f
0D
1i
0h
1J
1L
1W
1`
1b
1k
1m
0F
0I
0O
0Q
0R
0T
0\
0_
0e
0g
0j
1f
1^
1N
1H
1E
0)
0(
0V
0&
1c
1B
0K
0l
1'
0C
0Y
1)
1&
#2450
0-
0*
#2500
1-
1*
b1111 !
b1001 "
b100 #
b0 $
b10 %
b11010 /
0A
1@
0?
0=
0:
19
08
05
12
11
0L
0U
0W
0b
0k
0m
1D
1F
1I
1O
1Q
1R
1T
1\
1_
1e
1g
1h
1j
0d
0f
0[
0S
0P
0E
1l
1V
1K
0&
1X
1k
0)
#2550
0-
0*
#2600
1-
1*
b1011 !
b1110 "
b1100 #
b1010 $
b1 %
b11011 /
1A
0@
1>
1<
18
07
16
15
01
1P
0O
0Z
0H
0G
0]
1L
1U
1W
1b
1m
0D
0F
0I
0Q
0T
0\
0_
0g
0j
1f
1[
1S
1H
1E
0l
0a
0V
0K
1Y
1C
1&
1(
1)
0N
0c
1l
0)
#2650
0-
0*
#2700
1-
1*
b11 !
b110 "
b1110 #
b111 $
b10 %
b11100 /
0A
1@
1?
1=
0<
1:
04
00
0J
0L
0W
0`
0b
0m
1D
1F
1G
1I
1O
1Q
1T
1Z
1\
1]
1_
1g
1j
0f
0^
0[
0S
0M
0H
0B
1a
1V
1K
0'
1N
1c
0U
1'
#2750
0-
0*
#2800
1-
1*
b110 !
b1000 "
b1001 #
b1000 $
b0 %
b11101 /
0@
0?
0>
0=
1<
1;
0:
09
06
05
14
03
11
0P
1f
1S
1^
0i
1J
1L
1U
1W
1`
1b
1m
0l
0a
0'
0&
1d
0Y
0N
0c
1M
0V
1l
1'
#2850
0-
0*
#2900
1-
1*
b11 !
b100 "
b1011 $
b1 %
b11110 /
1A
1?
1>
15
04
13
01
1P
0f
0O
0]
0h
0F
0G
0I
0Q
0T
0\
0_
0g
0j
1i
1f
1[
1H
1Y
0X
1a
0(
#2950
0-
0*
#3000
1-
1*
b1001 !
b1101 "
b110 #
b1010 $
b10 %
b11111 /
0A
1@
0?
0;
1:
19
08
17
14
02
10
0J
0L
0W
0`
0b
0k
0m
1F
1G
1I
1O
1Q
1T
1\
1]
1_
1g
1h
1j
0d
0f
0^
0S
0M
0C
0E
1)
1(
1V
1&
0'
1B
1J
1N
1c
1k
0)
0U
0&
1'
#3050
0-
0*
#3100
1-
1*
b101 !
b110 "
b100 #
b111 $
b1 %
b100000 /
1A
0@
1?
1=
0<
0:
07
16
04
11
00
1E
0P
0Z
1^
0R
0h
1L
1U
1W
1`
1b
1m
0F
0I
0O
0Q
0T
0\
0]
0_
0g
0j
1f
1S
1P
0l
0(
0'
0K
1d
1X
1M
0B
1K
0V
0a
1)
0c
1l
1(
1'
0)
